phynteny-0.1.13.data/data/LICENSE
phynteny-0.1.13.data/data/README.md
phynteny-0.1.13.data/scripts/phynteny
phynteny_utils/__init__.py
phynteny_utils/current_models.txt
phynteny_utils/format_data.py
phynteny_utils/handle_genbank.py
phynteny_utils/install_models.py
phynteny_utils/models.py
phynteny_utils/predictor.py
phynteny_utils/statistics.py
phynteny_utils/train_model.py
phynteny_utils/phrog_annotation_info/confidence_kde.pkl
phynteny_utils/phrog_annotation_info/integer_category.pkl
phynteny_utils/phrog_annotation_info/phrog_annot_v4.tsv
phynteny_utils/phrog_annotation_info/phrog_integer.pkl
phynteny-0.1.13.dist-info/LICENSE
phynteny-0.1.13.dist-info/METADATA
phynteny-0.1.13.dist-info/WHEEL
phynteny-0.1.13.dist-info/entry_points.txt
phynteny-0.1.13.dist-info/top_level.txt
phynteny-0.1.13.dist-info/zip-safe
phynteny-0.1.13.dist-info/RECORD
