Metadata-Version: 2.1
Name: phynteny
Version: 0.1.13
Summary: Phynteny: Synteny-based prediction of bacteriophage genes
Home-page: https://github.com/susiegriggo/Phynteny
Author: Susanna Grigson
Author-email: susie.grigson@gmail.com
License: MIT
Classifier: Development Status :: 1 - Planning
Classifier: Programming Language :: Python :: 3
Classifier: License :: OSI Approved :: MIT License
Classifier: Natural Language :: English
Classifier: Topic :: Scientific/Engineering :: Bio-Informatics
Classifier: Operating System :: OS Independent
Requires-Python: <3.11
License-File: LICENSE
Requires-Dist: biopython >=1.79
Requires-Dist: scikit-learn <=1.2.2
Requires-Dist: numpy
Requires-Dist: pandas
Requires-Dist: click
Requires-Dist: joblib
Requires-Dist: loguru
Requires-Dist: tensorflow ==2.9.1
Requires-Dist: alive-progress >=3.0.1
Requires-Dist: requests >=2.25.1
